<?xml version="1.0" encoding="utf-8"?>
<dateplus>
	<start>
		<on day="7" month="12" year="2015" />
		<on day="25" month="12" year="2016" />
		<on day="13" month="12" year="2017" />
		<on day="3" month="21" year="2018" />
		<on day="23" month="12" year="2019" />
		<on day="11" month="12" year="2020" />
	</start>
	<end>
		<on day="15" month="12" year="2015" />
		<on day="2" month="1" year="2017" />
		<on day="21" month="12" year="2017" />
		<on day="11" month="12" year="2018" />
		<on day="31" month="12" year="2019" />
		<on day="19" month="12" year="2020" />
	</end>
</dateplus>
